umar/__init__.py
umar/add.py
umar/greet.py
umar-0.1.2.dist-info/METADATA
umar-0.1.2.dist-info/WHEEL
umar-0.1.2.dist-info/top_level.txt
umar-0.1.2.dist-info/RECORD
