Metadata-Version: 2.1
Name: umar
Version: 0.1.2
Summary: A simple Python package for greeting and adding numbers.
Home-page: https://github.com/umarmughal824/umar
Author: Umar Asghar
Author-email: mrumarasghar@gmail.com
Classifier: Programming Language :: Python :: 3
Classifier: License :: OSI Approved :: MIT License
Classifier: Operating System :: OS Independent
Requires-Python: >=3.6
